synctera_client_ng/__init__.py
synctera_client_ng/api/__init__.py
synctera_client_ng/api/accounts_api.py
synctera_client_ng/api/ach_api.py
synctera_client_ng/api/ach_transaction_simulations_api.py
synctera_client_ng/api/businesses_api.py
synctera_client_ng/api/card_transaction_simulations_api.py
synctera_client_ng/api/card_webhook_simulations_api.py
synctera_client_ng/api/cards_api.py
synctera_client_ng/api/cash_pickups_alpha_api.py
synctera_client_ng/api/customers_api.py
synctera_client_ng/api/digital_wallet_tokens_api.py
synctera_client_ng/api/disclosures_api.py
synctera_client_ng/api/disclosures_deprecated_api.py
synctera_client_ng/api/documents_api.py
synctera_client_ng/api/external_accounts_api.py
synctera_client_ng/api/external_cards_api.py
synctera_client_ng/api/internal_accounts_api.py
synctera_client_ng/api/internal_transfer_api.py
synctera_client_ng/api/international_wires_alpha_api.py
synctera_client_ng/api/kyc_verification_deprecated_api.py
synctera_client_ng/api/kyckyb_verifications_api.py
synctera_client_ng/api/licenses_api.py
synctera_client_ng/api/merchants_api.py
synctera_client_ng/api/monitoring_api.py
synctera_client_ng/api/notes_api.py
synctera_client_ng/api/payment_schedules_api.py
synctera_client_ng/api/persons_api.py
synctera_client_ng/api/reconciliations_api.py
synctera_client_ng/api/relationships_api.py
synctera_client_ng/api/remote_check_deposit_beta_api.py
synctera_client_ng/api/sandbox_wipe_alpha_api.py
synctera_client_ng/api/sandbox_wipe_api.py
synctera_client_ng/api/spend_controls_api.py
synctera_client_ng/api/spend_controls_beta_api.py
synctera_client_ng/api/statements_api.py
synctera_client_ng/api/transactions_api.py
synctera_client_ng/api/watchlist_deprecated_api.py
synctera_client_ng/api/webhooks_api.py
synctera_client_ng/api/wires_alpha_api.py
synctera_client_ng/api/wires_api.py
synctera_client_ng/api_client.py
synctera_client_ng/api_response.py
synctera_client_ng/configuration.py
synctera_client_ng/exceptions.py
synctera_client_ng-0.63.0.dist-info/METADATA
synctera_client_ng-0.63.0.dist-info/WHEEL
synctera_client_ng-0.63.0.dist-info/RECORD
